benchmark_qed/__init__.py
benchmark_qed/__main__.py
benchmark_qed/py.typed
benchmark_qed/autod/__init__.py
benchmark_qed/autod/data_model/__init__.py
benchmark_qed/autod/data_model/document.py
benchmark_qed/autod/data_model/identified.py
benchmark_qed/autod/data_model/text_unit.py
benchmark_qed/autod/data_processor/__init__.py
benchmark_qed/autod/data_processor/embedding.py
benchmark_qed/autod/data_processor/text_splitting.py
benchmark_qed/autod/data_processor/text_utils.py
benchmark_qed/autod/io/__init__.py
benchmark_qed/autod/io/document.py
benchmark_qed/autod/io/enums.py
benchmark_qed/autod/io/text_unit.py
benchmark_qed/autod/prompts/__init__.py
benchmark_qed/autod/prompts/summarization/__init__.py
benchmark_qed/autod/prompts/summarization/summary_map_system_prompt.txt
benchmark_qed/autod/prompts/summarization/summary_map_user_prompt.txt
benchmark_qed/autod/prompts/summarization/summary_reduce_system_prompt.txt
benchmark_qed/autod/prompts/summarization/summary_reduce_user_prompt.txt
benchmark_qed/autod/sampler/__init__.py
benchmark_qed/autod/sampler/enums.py
benchmark_qed/autod/sampler/sample_gen.py
benchmark_qed/autod/sampler/clustering/__init__.py
benchmark_qed/autod/sampler/clustering/base.py
benchmark_qed/autod/sampler/clustering/cluster.py
benchmark_qed/autod/sampler/clustering/constraint_kmeans.py
benchmark_qed/autod/sampler/clustering/kmeans.py
benchmark_qed/autod/sampler/neighboring/__init__.py
benchmark_qed/autod/sampler/neighboring/semantic_neighbors.py
benchmark_qed/autod/sampler/sampling/__init__.py
benchmark_qed/autod/sampler/sampling/attribute_sampler.py
benchmark_qed/autod/sampler/sampling/base.py
benchmark_qed/autod/sampler/sampling/kmeans_sampler.py
benchmark_qed/autod/sampler/sampling/random_sampler.py
benchmark_qed/autod/summarization/__init__.py
benchmark_qed/autod/summarization/base.py
benchmark_qed/autod/summarization/global_summarizer.py
benchmark_qed/autoe/__init__.py
benchmark_qed/autoe/assertion_scores.py
benchmark_qed/autoe/cli.py
benchmark_qed-0.3.0.dist-info/METADATA
benchmark_qed-0.3.0.dist-info/WHEEL
benchmark_qed-0.3.0.dist-info/entry_points.txt
benchmark_qed-0.3.0.dist-info/licenses/LICENSE
benchmark_qed-0.3.0.dist-info/RECORD
