Metadata-Version: 2.4
Name: benchmark-qed
Version: 0.3.0
Summary: BenchmarkQED: Automated benchmarking of retrieval-augmented generation (RAG) systems
Author-email: Andrés Morales Esquivel <andresmor@microsoft.com>, Darren Edge <daedge@microsoft.com>, Ha Trinh <trinhha@microsoft.com>
License-Expression: MIT
License-File: LICENSE
Requires-Python: >=3.11
Requires-Dist: aiohttp>=3.11.15
Requires-Dist: azure-ai-inference>=1.0.0b9
Requires-Dist: azure-identity>=1.22.0
Requires-Dist: fastparquet>=2024.11.0
Requires-Dist: json-repair>=0.44.1
Requires-Dist: nest-asyncio>=1.6.0
Requires-Dist: numpy>=2.2.0
Requires-Dist: openai>=1.68.2
Requires-Dist: pandas>=2.2.3
Requires-Dist: pyarrow>=19.0.1
Requires-Dist: pydantic>=2.10.4
Requires-Dist: python-dotenv>=1.0.1
Requires-Dist: pyyaml>=6.0.2
Requires-Dist: scikit-learn>=1.6.1
Requires-Dist: scipy>=1.14.1
Requires-Dist: statsmodels>=0.14.4
Requires-Dist: tiktoken>=0.9.0
Requires-Dist: typer>=0.15.1
